morrisseau_cleaner/__init__.py
morrisseau_cleaner/_version.py
morrisseau_cleaner/askii_art.py
morrisseau_cleaner/functions.py
morrisseau_cleaner/morrisseau_cleaner.py
morrisseau_cleaner/terminal.py
morrisseau_cleaner-0.11.1.dist-info/LICENSE
morrisseau_cleaner-0.11.1.dist-info/METADATA
morrisseau_cleaner-0.11.1.dist-info/WHEEL
morrisseau_cleaner-0.11.1.dist-info/entry_points.txt
morrisseau_cleaner-0.11.1.dist-info/top_level.txt
morrisseau_cleaner-0.11.1.dist-info/RECORD
