Metadata-Version: 2.1
Name: morrisseau-cleaner
Version: 0.11.1
Summary: A Python library to clean data for Morrisseau Project
Author: Ali Shajari
Author-email: ali0shajari@gmail.com
Classifier: Programming Language :: Python :: 3
Classifier: License :: OSI Approved :: MIT License
Classifier: Operating System :: OS Independent
Requires-Python: >=3.6
License-File: LICENSE
Requires-Dist: alabaster ==0.7.13
Requires-Dist: asttokens ==2.4.1
Requires-Dist: attr ==0.3.2
Requires-Dist: Babel ==2.13.1
Requires-Dist: boltons ==23.1.1
Requires-Dist: Brotli ==1.1.0
Requires-Dist: brotlicffi ==1.1.0.0
Requires-Dist: certifi ==2023.11.17
Requires-Dist: cffi ==1.16.0
Requires-Dist: charset-normalizer ==3.3.2
Requires-Dist: colorama ==0.4.6
Requires-Dist: comm ==0.2.0
Requires-Dist: configparser ==6.0.0
Requires-Dist: contextlib2 ==21.6.0
Requires-Dist: cryptography ==41.0.7
Requires-Dist: cx-Freeze ==6.15.11
Requires-Dist: Cython ==3.0.6
Requires-Dist: decorator ==5.1.1
Requires-Dist: docutils ==0.20.1
Requires-Dist: executing ==2.0.1
Requires-Dist: funcsigs ==1.0.2
Requires-Dist: HTMLParser ==0.0.2
Requires-Dist: idna ==3.6
Requires-Dist: imagesize ==1.4.1
Requires-Dist: importlib-metadata ==6.8.0
Requires-Dist: ipython ==8.18.1
Requires-Dist: ipywidgets ==8.1.1
Requires-Dist: jaraco.classes ==3.3.0
Requires-Dist: jedi ==0.19.1
Requires-Dist: Jinja2 ==3.1.2
Requires-Dist: jupyterlab-widgets ==3.0.9
Requires-Dist: keyring ==24.3.0
Requires-Dist: lockfile ==0.12.2
Requires-Dist: MarkupSafe ==2.1.3
Requires-Dist: matplotlib-inline ==0.1.6
Requires-Dist: mock ==5.1.0
Requires-Dist: more-itertools ==10.1.0
Requires-Dist: numpy ==1.26.2
Requires-Dist: packaging ==23.2
Requires-Dist: parso ==0.8.3
Requires-Dist: pexpect ==4.9.0
Requires-Dist: Pillow ==10.1.0
Requires-Dist: prompt-toolkit ==3.0.41
Requires-Dist: protobuf ==4.21.12
Requires-Dist: ptyprocess ==0.7.0
Requires-Dist: pure-eval ==0.2.2
Requires-Dist: pycparser ==2.21
Requires-Dist: pyfiglet ==1.0.2
Requires-Dist: Pygments ==2.17.2
Requires-Dist: pyOpenSSL ==23.3.0
Requires-Dist: railroad ==0.5.0
Requires-Dist: requests ==2.31.0
Requires-Dist: setuptools ==69.0.2
Requires-Dist: simplejson ==3.19.2
Requires-Dist: six ==1.16.0
Requires-Dist: snowballstemmer ==2.2.0
Requires-Dist: Sphinx ==7.2.6
Requires-Dist: sphinxcontrib-applehelp ==1.0.7
Requires-Dist: sphinxcontrib-devhelp ==1.0.5
Requires-Dist: sphinxcontrib-htmlhelp ==2.0.4
Requires-Dist: sphinxcontrib-jsmath ==1.0.1
Requires-Dist: sphinxcontrib-qthelp ==1.0.6
Requires-Dist: sphinxcontrib-serializinghtml ==1.1.9
Requires-Dist: stack-data ==0.6.3
Requires-Dist: termcolor ==2.3.0
Requires-Dist: thread ==0.1.2
Requires-Dist: toolz ==0.12.0
Requires-Dist: tornado ==6.4
Requires-Dist: traitlets ==5.14.0
Requires-Dist: truststore ==0.8.0
Requires-Dist: typing-extensions ==4.8.0
Requires-Dist: urllib3 ==2.1.0
Requires-Dist: urllib3-secure-extra ==0.1.0
Requires-Dist: wcwidth ==0.2.12
Requires-Dist: wheel ==0.42.0
Requires-Dist: widgetsnbextension ==4.0.9
Requires-Dist: zipp ==3.17.0
